[
    {
        "call": 6,
        "call_times": [
            "2019-02-22 07:50:55.233061",
            "2019-02-22 09:30:35.500477",
            "2019-02-22 11:30:36.682804",
            "2019-02-22 13:30:34.925855",
            "2019-02-22 15:30:35.654018"
        ],
        "day": 22,
        "name": "set_1",
        "runtimes": [
            "2019-02-22 07:30:00",
            "2019-02-22 09:30:00",
            "2019-02-22 11:30:00",
            "2019-02-22 13:30:00",
            "2019-02-22 15:30:00"
        ],
        "set": 1
    },
    {
        "call": 6,
        "call_times": [
            "2019-02-22 09:58:38.819813",
            "2019-02-22 11:45:36.362358",
            "2019-02-22 13:45:34.658392",
            "2019-02-22 15:45:34.704475",
            "2019-02-22 17:45:34.415882"
        ],
        "day": 22,
        "name": "set_2",
        "runtimes": [
            "2019-02-22 09:45:00",
            "2019-02-22 11:45:00",
            "2019-02-22 13:45:00",
            "2019-02-22 15:45:00",
            "2019-02-22 17:45:00"
        ],
        "set": 2
    },
    {
        "call": 6,
        "call_times": [
            "2019-02-22 12:10:46.489850",
            "2019-02-22 14:00:36.304286",
            "2019-02-22 16:00:33.340316",
            "2019-02-22 18:00:33.399203",
            "2019-02-22 20:00:33.509101"
        ],
        "day": 22,
        "name": "set_3",
        "runtimes": [
            "2019-02-22 12:00:00",
            "2019-02-22 14:00:00",
            "2019-02-22 16:00:00",
            "2019-02-22 18:00:00",
            "2019-02-22 20:00:00"
        ],
        "set": 3
    },
    {
        "call": 6,
        "call_times": [
            "2019-02-22 14:27:33.594186",
            "2019-02-22 16:15:35.295089",
            "2019-02-22 18:15:34.212762",
            "2019-02-22 20:15:35.590360",
            "2019-02-22 22:15:36.447750"
        ],
        "day": 22,
        "name": "set_4",
        "runtimes": [
            "2019-02-22 14:15:00",
            "2019-02-22 16:15:00",
            "2019-02-22 18:15:00",
            "2019-02-22 20:15:00",
            "2019-02-22 22:15:00"
        ],
        "set": 4
    },
    {
        "call": 6,
        "call_times": [
            "2019-02-22 16:43:46.795907",
            "2019-02-22 18:30:41.664605",
            "2019-02-22 20:30:35.422997",
            "2019-02-22 22:30:34.518294",
            "2019-02-23 00:30:33.893169"
        ],
        "day": 22,
        "name": "set_5",
        "runtimes": [
            "2019-02-22 16:30:00",
            "2019-02-22 18:30:00",
            "2019-02-22 20:30:00",
            "2019-02-22 22:30:00",
            "2019-02-23 00:30:00"
        ],
        "set": 5
    },
    {
        "call": 6,
        "call_times": [
            "2019-02-22 18:58:12.300419",
            "2019-02-22 20:45:43.757556",
            "2019-02-22 22:45:35.237469",
            "2019-02-23 00:45:34.758345",
            "2019-02-23 02:45:34.928936"
        ],
        "day": 22,
        "name": "set_6",
        "runtimes": [
            "2019-02-22 18:45:00",
            "2019-02-22 20:45:00",
            "2019-02-22 22:45:00",
            "2019-02-23 00:45:00",
            "2019-02-23 02:45:00"
        ],
        "set": 6
    }
]